mutwo/abjad_converters/__init__.py
mutwo/abjad_converters/configurations.py
mutwo/abjad_converters/constants.py
mutwo/abjad_converters/process_container_routines.py
mutwo/abjad_converters/events/__init__.py
mutwo/abjad_converters/events/building.py
mutwo/abjad_converters/events/quantization.py
mutwo/abjad_converters/parameters/__init__.py
mutwo/abjad_converters/parameters/heji.py
mutwo/abjad_converters/parameters/lyrics.py
mutwo/abjad_converters/parameters/pitches.py
mutwo/abjad_converters/parameters/tempos.py
mutwo/abjad_converters/parameters/volumes.py
mutwo/abjad_parameters/__init__.py
mutwo/abjad_parameters/abc.py
mutwo/abjad_parameters/attachments.py
mutwo/abjad_parameters/configurations.py
mutwo/abjad_parameters/constants.py
mutwo/abjad_utilities/__init__.py
mutwo/abjad_utilities/abjad.py
mutwo/abjad_utilities/exceptions.py
mutwo/abjad_utilities/tests.py
mutwo/abjad_utilities/tools.py
mutwo/abjad_version/__init__.py
mutwo_third_party/abjad/__init__.py
mutwo.abjad-0.20.0.dist-info/LICENSE
mutwo.abjad-0.20.0.dist-info/METADATA
mutwo.abjad-0.20.0.dist-info/WHEEL
mutwo.abjad-0.20.0.dist-info/top_level.txt
mutwo.abjad-0.20.0.dist-info/RECORD
