Metadata-Version: 2.1
Name: mutwo.abjad
Version: 0.20.0
Summary: abjad extension for event based framework mutwo
Home-page: https://github.com/mutwo-org/mutwo.abjad
Author: Levin Eric Zimmermann
Author-email: levin.eric.zimmermann@posteo.eu
License: GPL
Project-URL: Documentation, https://mutwo-org.github.io
Requires-Python: >=3.10, <4
License-File: LICENSE
Requires-Dist: mutwo.core <3.0.0,>=2.0.0
Requires-Dist: mutwo.music <1.0.0,>=0.27.0
Requires-Dist: abjad <3.12.0,>=3.9.0
Requires-Dist: abjad-ext-nauert <3.12.0,>=3.9.0
Requires-Dist: python-ranges <2.0.0,>=1.2.0
Provides-Extra: testing
Requires-Dist: pytest >=7.1.1 ; extra == 'testing'
Requires-Dist: mutwo.ekmelily <1.0.0,>=0.9.0 ; extra == 'testing'
